random_readline/__init__.py
random_readline/_read_line.py
random_readline-0.1.0.dist-info/LICENSE
random_readline-0.1.0.dist-info/METADATA
random_readline-0.1.0.dist-info/WHEEL
random_readline-0.1.0.dist-info/top_level.txt
random_readline-0.1.0.dist-info/RECORD
