Metadata-Version: 2.1
Name: random-readline
Version: 0.1.0
Summary: Randomized fast readline for large text files.
Home-page: https://github.com/yuhsak/random-readline
Author: Yuhsak Inoue
Author-email: yuhsak.inoue@gmail.com
Maintainer: Yuhsak Inoue
Maintainer-email: yuhsak.inoue@gmail.com
License: MIT
Download-URL: https://github.com/yuhsak/random-readline
Platform: UNKNOWN
License-File: LICENSE
